comments_wagtail_xtd/__init__.py
comments_wagtail_xtd/urls.py
comments_wagtail_xtd/utils.py
comments_wagtail_xtd/views.py
comments_wagtail_xtd/wagtail_hooks.py
comments_wagtail_xtd/templates/comments_wagtail_xtd/comments.html
comments_wagtail_xtd/templates/comments_wagtail_xtd/comments_summary.html
comments_wagtail_xtd/templates/comments_wagtail_xtd/latest_comments.html
comments_wagtail_xtd/templates/comments_wagtail_xtd/layout.html
comments_wagtail_xtd/templates/comments_wagtail_xtd/pages.html
comments_wagtail_xtd/templates/comments_wagtail_xtd/comments/_list_explore.html
comments_wagtail_xtd/templates/comments_wagtail_xtd/comments/_list_latest_explore.html
comments_wagtail_xtd/templates/comments_wagtail_xtd/comments/_table_headers_explore.html
comments_wagtail_xtd/templates/comments_wagtail_xtd/pages/_list.html
comments_wagtail_xtd/templates/comments_wagtail_xtd/pages/_table_headers_explore.html
comments_wagtail_xtd/templates/comments_wagtail_xtd/partials/comments_breadcrumb.html
comments_wagtail_xtd/templatetags/__init__.py
comments_wagtail_xtd/templatetags/comments_wagtail_xtd_tags.py
comments_wagtail_xtd-1.0.4.dist-info/LICENSE
comments_wagtail_xtd-1.0.4.dist-info/METADATA
comments_wagtail_xtd-1.0.4.dist-info/WHEEL
comments_wagtail_xtd-1.0.4.dist-info/top_level.txt
comments_wagtail_xtd-1.0.4.dist-info/RECORD
