Metadata-Version: 2.1
Name: comments-wagtail-xtd
Version: 1.0.4
Summary: UNKNOWN
Home-page: https://github.com/AlexDeltax/wagtail_comments_xtd
Author: Alexander Smolenskyi
Author-email: alexsmolenskyi@gmail.com
License: GPLv3
Platform: UNKNOWN
Classifier: Environment :: Web Environment
Classifier: Framework :: Django
Classifier: Intended Audience :: Developers
Classifier: Operating System :: OS Independent
Classifier: Programming Language :: Python
Classifier: Topic :: Internet :: WWW/HTTP
Classifier: Topic :: Internet :: WWW/HTTP :: Dynamic Content
Requires-Python: >=3.9
License-File: LICENSE
Requires-Dist: wagtail (>=2.15.1)
Requires-Dist: Django (>=4.0.0)
Requires-Dist: wagtailfontawesome (>=1.2.1)
Requires-Dist: django-comments-xtd (>=2.9.5)
